PyHLV/__init__.py
PyHLV/main.py
PyHLV/PyHLV.py
PyHLV/__main__.py
PyHLV-1.2.4.dist-info/RECORD
PyHLV-1.2.4.dist-info/metadata.json
PyHLV-1.2.4.dist-info/WHEEL
PyHLV-1.2.4.dist-info/entry_points.txt
PyHLV-1.2.4.dist-info/DESCRIPTION.rst
PyHLV-1.2.4.dist-info/top_level.txt
PyHLV-1.2.4.dist-info/METADATA
